Engine/__init__.py
Engine/components.py
Engine/config.py
Engine/engine.py
Engine/events.py
Engine/input.py
Engine/logger.py
Engine/resources.py
Engine/time.py
Engine/utils.py
Engine/window.py
IntPy/__init__.py
IntPy/advanced_math.py
IntPy/geometry.py
IntPy/math3d.py
IntPy/math_utils.py
IntPy/matrices.py
IntPy/quaternion.py
IntPy/vectors.py
Render_Pipeline/__init__.py
Render_Pipeline/camera.py
Render_Pipeline/geometry.py
Render_Pipeline/light.py
Render_Pipeline/material.py
Render_Pipeline/render_pipeline.py
Render_Pipeline/scene.py
Render_Pipeline/transform.py
axis3-1.0.0.dist-info/licenses/LICENSE
axis3-1.0.0.dist-info/METADATA
axis3-1.0.0.dist-info/WHEEL
axis3-1.0.0.dist-info/top_level.txt
axis3-1.0.0.dist-info/RECORD
