Metadata-Version: 2.4
Name: axis3
Version: 1.0.0
Summary: A powerful Python game engine with comprehensive math library and render pipeline
Home-page: https://github.com/yourusername/core
Author: Core Contributors
Author-email: 
License: MIT
Project-URL: Homepage, https://github.com/yourusername/core
Keywords: core,3d,rendering,math,graphics
Classifier: Development Status :: 4 - Beta
Classifier: Intended Audience :: Developers
Classifier: License :: OSI Approved :: MIT License
Classifier: Programming Language :: Python :: 3
Classifier: Programming Language :: Python :: 3.8
Classifier: Programming Language :: Python :: 3.9
Classifier: Programming Language :: Python :: 3.10
Classifier: Programming Language :: Python :: 3.11
Classifier: Topic :: Games/Entertainment
Classifier: Topic :: Multimedia :: Graphics
Classifier: Topic :: Software Development :: Libraries
Requires-Python: >=3.8
License-File: LICENSE
Provides-Extra: dev
Requires-Dist: pytest>=7.0; extra == "dev"
Requires-Dist: black>=22.0; extra == "dev"
Requires-Dist: flake8>=4.0; extra == "dev"
Dynamic: home-page
Dynamic: license-file
Dynamic: requires-python
